picoanim/__init__.py
picoanim/animation.py
picoanim/cli.py
picoanim/colors.py
picoanim/easing.py
picoanim/mobject.py
picoanim/renderer.py
picoanim/scene.py
picoanim/shapes.py
picoanim-0.1.0.dist-info/licenses/LICENSE
picoanim-0.1.0.dist-info/METADATA
picoanim-0.1.0.dist-info/WHEEL
picoanim-0.1.0.dist-info/entry_points.txt
picoanim-0.1.0.dist-info/top_level.txt
picoanim-0.1.0.dist-info/RECORD
