Metadata-Version: 2.4
Name: picoanim
Version: 0.1.0
Summary: Tiny 2D programmatic animation engine inspired by manim
Author: Your Name
License: MIT
Project-URL: Homepage, https://example.com
Keywords: animation,graphics,manim,pillow,imageio
Classifier: Development Status :: 3 - Alpha
Classifier: Intended Audience :: Developers
Classifier: License :: OSI Approved :: MIT License
Classifier: Programming Language :: Python :: 3
Classifier: Programming Language :: Python :: 3 :: Only
Classifier: Programming Language :: Python :: 3.9
Classifier: Programming Language :: Python :: 3.10
Classifier: Programming Language :: Python :: 3.11
Classifier: Programming Language :: Python :: 3.12
Classifier: Operating System :: OS Independent
Classifier: Topic :: Multimedia :: Graphics
Classifier: Topic :: Multimedia :: Video
Requires-Python: >=3.9
License-File: LICENSE
Requires-Dist: Pillow>=10.0.0
Requires-Dist: imageio>=2.31.0
Requires-Dist: imageio-ffmpeg>=0.4.9
Requires-Dist: numpy>=1.21.0
Provides-Extra: dev
Requires-Dist: pytest>=7.0; extra == "dev"
Requires-Dist: build>=1.0.0; extra == "dev"
Requires-Dist: twine>=5.0.0; extra == "dev"
Dynamic: license-file
